README.md
setup.py
piotrhow_hello_world.egg-info/PKG-INFO
piotrhow_hello_world.egg-info/SOURCES.txt
piotrhow_hello_world.egg-info/dependency_links.txt
piotrhow_hello_world.egg-info/top_level.txt
sample_package/__init__.py
sample_package/sample.py